relativetimebuilder/__init__.py
relativetimebuilder/version.py
relativetimebuilder/tests/__init__.py
relativetimebuilder/tests/test_init.py
relativetimebuilder-3.0.2.dist-info/licenses/LICENSE
relativetimebuilder-3.0.2.dist-info/METADATA
relativetimebuilder-3.0.2.dist-info/WHEEL
relativetimebuilder-3.0.2.dist-info/top_level.txt
relativetimebuilder-3.0.2.dist-info/RECORD
