Metadata-Version: 2.4
Name: relativetimebuilder
Version: 3.0.2
Summary: A library for using the dateutil relativedeltas for calendar precision with aniso8601
Home-page: https://codeberg.org/nielsenb-jf/relativetimebuilder
Author: Brandon Nielsen
Author-email: nielsenb@jetfuse.net
Project-URL: Changelog, https://codeberg.org/nielsenb-jf/relativetimebuilder/src/branch/main/CHANGELOG.rst
Project-URL: Documentation, https://relativetimebuilder.readthedocs.io/
Project-URL: Source, https://codeberg.org/nielsenb-jf/relativetimebuilder
Project-URL: Tracker, https://codeberg.org/nielsenb-jf/relativetimebuilder/issues
Keywords: iso8601 dateutil aniso8601 datetime
Classifier: Development Status :: 5 - Production/Stable
Classifier: Intended Audience :: Developers
Classifier: License :: OSI Approved :: BSD License
Classifier: Operating System :: OS Independent
Classifier: Programming Language :: Python
Classifier: Programming Language :: Python :: 2
Classifier: Programming Language :: Python :: 2.7
Classifier: Programming Language :: Python :: 3
Classifier: Programming Language :: Python :: 3.9
Classifier: Programming Language :: Python :: 3.10
Classifier: Programming Language :: Python :: 3.11
Classifier: Programming Language :: Python :: 3.12
Classifier: Programming Language :: Python :: 3.13
Classifier: Topic :: Software Development :: Libraries :: Python Modules
License-File: LICENSE
Requires-Dist: aniso8601<11.0.0,>=9.0.0
Requires-Dist: python-dateutil>=2.7.3
Provides-Extra: dev
Requires-Dist: black; extra == "dev"
Requires-Dist: coverage; extra == "dev"
Requires-Dist: isort; extra == "dev"
Requires-Dist: pre-commit; extra == "dev"
Requires-Dist: pyenchant; extra == "dev"
Requires-Dist: pylint; extra == "dev"
Dynamic: author
Dynamic: author-email
Dynamic: classifier
Dynamic: description
Dynamic: description-content-type
Dynamic: home-page
Dynamic: keywords
Dynamic: license-file
Dynamic: project-url
Dynamic: provides-extra
Dynamic: requires-dist
Dynamic: summary
